bin/kalle_conversations
bin/kalle_patterns
kalle/__init__.py
kalle/cli/conversationmanager.py
kalle/cli/conversationmanager_layouts.tcss
kalle/cli/kalle.py
kalle/cli/patterneditor.py
kalle/cli/profiles.py
kalle/cli/prompt.py
kalle/cli/sigint_clean_exit.py
kalle/cli/tools.py
kalle/data/README.md
kalle/data/config.yml.example
kalle/data/tokenizer_config/codestral/README.md
kalle/data/tokenizer_config/codestral/config.json
kalle/data/tokenizer_config/codestral/special_tokens_map.json
kalle/data/tokenizer_config/codestral/tokenizer.json
kalle/data/tokenizer_config/codestral/tokenizer_config.json
kalle/data/tokenizer_config/gemma2/README.md
kalle/data/tokenizer_config/gemma2/config.json
kalle/data/tokenizer_config/gemma2/generation_config.json
kalle/data/tokenizer_config/gemma2/special_tokens_map.json
kalle/data/tokenizer_config/gemma2/tokenizer.json
kalle/data/tokenizer_config/gemma2/tokenizer.model
kalle/data/tokenizer_config/gemma2/tokenizer_config.json
kalle/data/tokenizer_config/llama3/.gitattributes
kalle/data/tokenizer_config/llama3/LICENSE
kalle/data/tokenizer_config/llama3/README.md
kalle/data/tokenizer_config/llama3/USE_POLICY.md
kalle/data/tokenizer_config/llama3/config.json
kalle/data/tokenizer_config/llama3/tokenizer.json
kalle/data/tokenizer_config/llama3/tokenizer_config.json
kalle/data/tokenizer_config/llama3_1/LICENSE
kalle/data/tokenizer_config/llama3_1/README.md
kalle/data/tokenizer_config/llama3_1/config.json
kalle/data/tokenizer_config/llama3_1/generation_config.json
kalle/data/tokenizer_config/llama3_1/model.safetensors.index.json
kalle/data/tokenizer_config/llama3_1/special_tokens_map.json
kalle/data/tokenizer_config/llama3_1/tokenizer.json
kalle/data/tokenizer_config/llama3_1/tokenizer_config.json
kalle/data/tokenizer_config/mistrallarge/README.md
kalle/data/tokenizer_config/mistrallarge/config.json
kalle/data/tokenizer_config/mistrallarge/consolidated.safetensors.index.json
kalle/data/tokenizer_config/mistrallarge/generation_config.json
kalle-0.0.6.dist-info/licenses/LICENSE.md
kalle-0.0.6.dist-info/METADATA
kalle-0.0.6.dist-info/WHEEL
kalle-0.0.6.dist-info/entry_points.txt
kalle-0.0.6.dist-info/top_level.txt
kalle-0.0.6.dist-info/RECORD
