Metadata-Version: 2.4
Name: kalle
Version: 0.0.6
Summary: A smart CLI friend
Project-URL: Homepage, https://codeberg.org/fe2/kalle
Project-URL: Repository, https://codeberg.org/fe2/kalle
Project-URL: Issues, https://codeberg.org/fe2/kalle/issues
Project-URL: Documentation, https://codeberg.org/fe2/kalle/src/branch/main/docs
Requires-Python: <3.13,>=3.12
License-File: LICENSE.md
Requires-Dist: aiohttp>=3.12.15
Requires-Dist: anthropic>=0.69.0
Requires-Dist: atproto>=0.0.62
Requires-Dist: bs4>=0.0.2
Requires-Dist: coverage>=7.10.7
Requires-Dist: docling>=2.55.1
Requires-Dist: espeakng>=1.0.3
Requires-Dist: fastapi>=0.118.0
Requires-Dist: fastembed>=0.7.3
Requires-Dist: google>=3.0.0
Requires-Dist: google-api-python-client>=2.184.0
Requires-Dist: google-auth>=2.41.1
Requires-Dist: google-auth-oauthlib>=1.2.2
Requires-Dist: groq>=0.32.0
Requires-Dist: httpx==0.27.2
Requires-Dist: llama-cpp-python>=0.3.16
Requires-Dist: markdownify>=1.2.0
Requires-Dist: mistral-common>=1.8.5
Requires-Dist: openai>=2.1.0
Requires-Dist: pip>=25.0.1
Requires-Dist: pip-licenses>=5.0.0
Requires-Dist: platformdirs>=4.4.0
Requires-Dist: pydantic>=2.11.10
Requires-Dist: pydantic-settings>=2.11.0
Requires-Dist: pypdf>=6.1.1
Requires-Dist: pyright>=1.1.406
Requires-Dist: pyserial>=3.5
Requires-Dist: python-magic>=0.4.27
Requires-Dist: pytz>=2025.2
Requires-Dist: pyyaml>=6.0.3
Requires-Dist: rich>=14.1.0
Requires-Dist: rich-argparse>=1.7.1
Requires-Dist: ruff>=0.13.3
Requires-Dist: sentencepiece>=0.2.1
Requires-Dist: sqlite-vec>=0.1.6
Requires-Dist: tenacity>=9.1.2
Requires-Dist: textual>=6.2.1
Requires-Dist: tiktoken>=0.11.0
Requires-Dist: transformers>=4.57.0
Requires-Dist: uvicorn>=0.37.0
Requires-Dist: vertexai>=1.71.1
Dynamic: license-file
